reques_smm/__init__.py
reques_smm/api.py
reques_smm/scrapt.py
reques_smm/utlites.py
reques_smm-0.0.0.5.dist-info/licenses/LICENSE
reques_smm-0.0.0.5.dist-info/METADATA
reques_smm-0.0.0.5.dist-info/WHEEL
reques_smm-0.0.0.5.dist-info/top_level.txt
reques_smm-0.0.0.5.dist-info/RECORD
