Metadata-Version: 2.4
Name: reques_smm
Version: 0.0.0.5
Summary: A library for manipulating memory in a Windows process
Home-page: https://github.com/Mahdi-hasan-shuvo/PyMemoryRW
Author: Mahdi Hasan Shuvo
Author-email: shuvobbhh@gmail.com
License: MIT
Project-URL: Homepage, https://github.com/Mahdi-hasan-shuvo/PyMemoryRW
Project-URL: Bug Reports, https://github.com/Mahdi-hasan-shuvo/PyMemoryRW/issues
Project-URL: Source, https://github.com/Mahdi-hasan-shuvo/PyMemoryRW
Keywords: memory manipulation Windows memory management process memory Windows API memory injection memory editing Windows process memory library process hacking Windows utilities memory access system programming memory tools Win32 API Python memory library process manipulation memory read/write Windows programming memory management library Python Windows API
Classifier: Programming Language :: Python :: 3
Classifier: License :: OSI Approved :: MIT License
Classifier: Operating System :: OS Independent
Requires-Python: >=3.11
License-File: LICENSE
Requires-Dist: some_dependency
Dynamic: author
Dynamic: author-email
Dynamic: classifier
Dynamic: description
Dynamic: description-content-type
Dynamic: home-page
Dynamic: keywords
Dynamic: license
Dynamic: license-file
Dynamic: project-url
Dynamic: requires-dist
Dynamic: requires-python
Dynamic: summary
